[
    {
        "slo": 1.0,
        "cost": 20.756,
        "lam": 585,
        "node_configs": {
            "res50": {
                "name": "res50",
                "num_cpus": 1,
                "gpu_type": "v100",
                "batch_size": 23.935555555555556,
                "num_replicas": 3,
                "cloud": "aws",
                "p99_lat": 0.257824,
                "estimated_thru": 474.0
            },
            "res152": {
                "name": "res152",
                "num_cpus": 1,
                "gpu_type": "v100",
                "batch_size": 2.0,
                "num_replicas": 1,
                "cloud": "aws",
                "p99_lat": 0.08200469999999999,
                "estimated_thru": 47.6
            },
            "alexnet": {
                "name": "alexnet",
                "num_cpus": 1,
                "gpu_type": "v100",
                "batch_size": 3.993333333333333,
                "num_replicas": 4,
                "cloud": "aws",
                "p99_lat": 0.06158179,
                "estimated_thru": 686.0
            }
        },
        "estimated_perf": {
            "latency": 0.40141049,
            "throughput": 585.4511784511785,
            "cost": 20.756
        },
        "response_time": 0.8651954721849813,
        "cv": 0.1,
        "utilization": 1.0,
        "latency_percentage": 1.0
    },
    {
        "slo": 1.0,
        "cost": 18.1615,
        "lam": 531,
        "node_configs": {
            "res50": {
                "name": "res50",
                "num_cpus": 1,
                "gpu_type": "v100",
                "batch_size": 12.0,
                "num_replicas": 3,
                "cloud": "aws",
                "p99_lat": 0.16875626999999996,
                "estimated_thru": 466.20000000000005
            },
            "res152": {
                "name": "res152",
                "num_cpus": 1,
                "gpu_type": "v100",
                "batch_size": 2.0,
                "num_replicas": 1,
                "cloud": "aws",
                "p99_lat": 0.08200469999999999,
                "estimated_thru": 47.6
            },
            "alexnet": {
                "name": "alexnet",
                "num_cpus": 1,
                "gpu_type": "v100",
                "batch_size": 12.0,
                "num_replicas": 3,
                "cloud": "aws",
                "p99_lat": 0.12807974999999994,
                "estimated_thru": 529.8
            }
        },
        "estimated_perf": {
            "latency": 0.37884071999999985,
            "throughput": 529.8,
            "cost": 18.1615
        },
        "response_time": 0.8847848581856885,
        "cv": 0.1,
        "utilization": 1.0,
        "latency_percentage": 1.0
    },
    {
        "slo": 1.0,
        "cost": 15.567,
        "lam": 388,
        "node_configs": {
            "res50": {
                "name": "res50",
                "num_cpus": 1,
                "gpu_type": "v100",
                "batch_size": 23.935555555555556,
                "num_replicas": 2,
                "cloud": "aws",
                "p99_lat": 0.257824,
                "estimated_thru": 316.0
            },
            "res152": {
                "name": "res152",
                "num_cpus": 1,
                "gpu_type": "v100",
                "batch_size": 2.0,
                "num_replicas": 1,
                "cloud": "aws",
                "p99_lat": 0.08200469999999999,
                "estimated_thru": 47.6
            },
            "alexnet": {
                "name": "alexnet",
                "num_cpus": 1,
                "gpu_type": "v100",
                "batch_size": 3.993333333333333,
                "num_replicas": 3,
                "cloud": "aws",
                "p99_lat": 0.06158179,
                "estimated_thru": 514.5
            }
        },
        "estimated_perf": {
            "latency": 0.40141049,
            "throughput": 390.300785634119,
            "cost": 15.567
        },
        "response_time": 0.8795249196743314,
        "cv": 0.1,
        "utilization": 1.0,
        "latency_percentage": 1.0
    },
    {
        "slo": 1.0,
        "cost": 12.9725,
        "lam": 353,
        "node_configs": {
            "res50": {
                "name": "res50",
                "num_cpus": 1,
                "gpu_type": "v100",
                "batch_size": 12.0,
                "num_replicas": 2,
                "cloud": "aws",
                "p99_lat": 0.16875626999999996,
                "estimated_thru": 310.8
            },
            "res152": {
                "name": "res152",
                "num_cpus": 1,
                "gpu_type": "v100",
                "batch_size": 2.0,
                "num_replicas": 1,
                "cloud": "aws",
                "p99_lat": 0.08200469999999999,
                "estimated_thru": 47.6
            },
            "alexnet": {
                "name": "alexnet",
                "num_cpus": 1,
                "gpu_type": "v100",
                "batch_size": 12.0,
                "num_replicas": 2,
                "cloud": "aws",
                "p99_lat": 0.12807974999999994,
                "estimated_thru": 353.2
            }
        },
        "estimated_perf": {
            "latency": 0.37884071999999985,
            "throughput": 353.2,
            "cost": 12.9725
        },
        "response_time": 0.949892444057659,
        "cv": 0.1,
        "utilization": 1.0,
        "latency_percentage": 1.0
    },
    {
        "slo": 1.0,
        "cost": 10.378,
        "lam": 194,
        "node_configs": {
            "res50": {
                "name": "res50",
                "num_cpus": 1,
                "gpu_type": "v100",
                "batch_size": 23.935555555555556,
                "num_replicas": 1,
                "cloud": "aws",
                "p99_lat": 0.257824,
                "estimated_thru": 158.0
            },
            "res152": {
                "name": "res152",
                "num_cpus": 1,
                "gpu_type": "v100",
                "batch_size": 2.0,
                "num_replicas": 1,
                "cloud": "aws",
                "p99_lat": 0.08200469999999999,
                "estimated_thru": 47.6
            },
            "alexnet": {
                "name": "alexnet",
                "num_cpus": 1,
                "gpu_type": "v100",
                "batch_size": 2.0,
                "num_replicas": 2,
                "cloud": "aws",
                "p99_lat": 0.04475594999999999,
                "estimated_thru": 254.0
            }
        },
        "estimated_perf": {
            "latency": 0.38458465,
            "throughput": 195.1503928170595,
            "cost": 10.378
        },
        "response_time": 0.9115262678689225,
        "cv": 0.1,
        "utilization": 1.0,
        "latency_percentage": 1.0
    },
    {
        "slo": 1.0,
        "cost": 7.7835,
        "lam": 183,
        "node_configs": {
            "res50": {
                "name": "res50",
                "num_cpus": 1,
                "gpu_type": "v100",
                "batch_size": 8.0,
                "num_replicas": 1,
                "cloud": "aws",
                "p99_lat": 0.11880813000000001,
                "estimated_thru": 150.4
            },
            "res152": {
                "name": "res152",
                "num_cpus": 1,
                "gpu_type": "v100",
                "batch_size": 2.0,
                "num_replicas": 1,
                "cloud": "aws",
                "p99_lat": 0.08200469999999999,
                "estimated_thru": 47.6
            },
            "alexnet": {
                "name": "alexnet",
                "num_cpus": 1,
                "gpu_type": "v100",
                "batch_size": 24.0,
                "num_replicas": 1,
                "cloud": "aws",
                "p99_lat": 0.24202966000000004,
                "estimated_thru": 186.2
            }
        },
        "estimated_perf": {
            "latency": 0.44284249000000003,
            "throughput": 185.76341189674525,
            "cost": 7.7835
        },
        "response_time": 0.9816991415498659,
        "cv": 0.1,
        "utilization": 1.0,
        "latency_percentage": 1.0
    }
]