[
    {
        "slo": 1.0,
        "cost": 5.4,
        "lam": 141,
        "node_configs": {
            "inception": {
                "name": "inception",
                "num_cpus": 1,
                "gpu_type": "v100",
                "batch_size": 16.0,
                "num_replicas": 1,
                "cloud": "aws"
            },
            "tf-resnet-feats": {
                "name": "tf-resnet-feats",
                "num_cpus": 1,
                "gpu_type": "v100",
                "batch_size": 48.0,
                "num_replicas": 1,
                "cloud": "aws"
            },
            "tf-log-reg": {
                "name": "tf-log-reg",
                "num_cpus": 1,
                "gpu_type": "none",
                "batch_size": 1,
                "num_replicas": 1,
                "cloud": "aws"
            },
            "tf-kernel-svm": {
                "name": "tf-kernel-svm",
                "num_cpus": 1,
                "gpu_type": "none",
                "batch_size": 4.0,
                "num_replicas": 1,
                "cloud": "aws"
            }
        },
        "estimated_perf": {
            "latency": 0.2473591,
            "throughput": 167.18244529019978,
            "cost": 5.321999999999999
        },
        "response_time": 0.8594016142612584,
        "cv": 4.0,
        "utilization": 0.7
    },
    {
        "slo": 1.0,
        "cost": 8.0,
        "lam": 209,
        "node_configs": {
            "inception": {
                "name": "inception",
                "num_cpus": 1,
                "gpu_type": "v100",
                "batch_size": 48.0,
                "num_replicas": 1,
                "cloud": "aws"
            },
            "tf-resnet-feats": {
                "name": "tf-resnet-feats",
                "num_cpus": 1,
                "gpu_type": "v100",
                "batch_size": 24.0,
                "num_replicas": 2,
                "cloud": "aws"
            },
            "tf-log-reg": {
                "name": "tf-log-reg",
                "num_cpus": 1,
                "gpu_type": "none",
                "batch_size": 1,
                "num_replicas": 1,
                "cloud": "aws"
            },
            "tf-kernel-svm": {
                "name": "tf-kernel-svm",
                "num_cpus": 1,
                "gpu_type": "none",
                "batch_size": 8.0,
                "num_replicas": 1,
                "cloud": "aws"
            }
        },
        "estimated_perf": {
            "latency": 0.20243355000000002,
            "throughput": 227.77999999999997,
            "cost": 7.916499999999999
        },
        "response_time": 0.9369498290372311,
        "cv": 4.0,
        "utilization": 0.7
    },
    {
        "slo": 1.0,
        "cost": 10.6,
        "lam": 310,
        "node_configs": {
            "inception": {
                "name": "inception",
                "num_cpus": 1,
                "gpu_type": "v100",
                "batch_size": 16.0,
                "num_replicas": 2,
                "cloud": "aws"
            },
            "tf-resnet-feats": {
                "name": "tf-resnet-feats",
                "num_cpus": 1,
                "gpu_type": "v100",
                "batch_size": 48.0,
                "num_replicas": 2,
                "cloud": "aws"
            },
            "tf-log-reg": {
                "name": "tf-log-reg",
                "num_cpus": 1,
                "gpu_type": "none",
                "batch_size": 1,
                "num_replicas": 1,
                "cloud": "aws"
            },
            "tf-kernel-svm": {
                "name": "tf-kernel-svm",
                "num_cpus": 1,
                "gpu_type": "none",
                "batch_size": 8.0,
                "num_replicas": 1,
                "cloud": "aws"
            }
        },
        "estimated_perf": {
            "latency": 0.24908517000000002,
            "throughput": 334.36489058039956,
            "cost": 10.511
        },
        "response_time": 0.865697160397491,
        "cv": 4.0,
        "utilization": 0.7
    },
    {
        "slo": 1.0,
        "cost": 13.2,
        "lam": 448,
        "node_configs": {
            "inception": {
                "name": "inception",
                "num_cpus": 1,
                "gpu_type": "v100",
                "batch_size": 64.0,
                "num_replicas": 2,
                "cloud": "aws"
            },
            "tf-resnet-feats": {
                "name": "tf-resnet-feats",
                "num_cpus": 1,
                "gpu_type": "v100",
                "batch_size": 32.0,
                "num_replicas": 3,
                "cloud": "aws"
            },
            "tf-log-reg": {
                "name": "tf-log-reg",
                "num_cpus": 1,
                "gpu_type": "none",
                "batch_size": 1,
                "num_replicas": 1,
                "cloud": "aws"
            },
            "tf-kernel-svm": {
                "name": "tf-kernel-svm",
                "num_cpus": 1,
                "gpu_type": "none",
                "batch_size": 12.0,
                "num_replicas": 1,
                "cloud": "aws"
            }
        },
        "estimated_perf": {
            "latency": 0.25372732,
            "throughput": 458.91999999999996,
            "cost": 13.1055
        },
        "response_time": 0.9912572506300712,
        "cv": 4.0,
        "utilization": 0.7
    },
    {
        "slo": 1.0,
        "cost": 15.8,
        "lam": 482,
        "node_configs": {
            "inception": {
                "name": "inception",
                "num_cpus": 1,
                "gpu_type": "v100",
                "batch_size": 32.0,
                "num_replicas": 3,
                "cloud": "aws"
            },
            "tf-resnet-feats": {
                "name": "tf-resnet-feats",
                "num_cpus": 1,
                "gpu_type": "v100",
                "batch_size": 64.0,
                "num_replicas": 3,
                "cloud": "aws"
            },
            "tf-log-reg": {
                "name": "tf-log-reg",
                "num_cpus": 1,
                "gpu_type": "none",
                "batch_size": 1,
                "num_replicas": 1,
                "cloud": "aws"
            },
            "tf-kernel-svm": {
                "name": "tf-kernel-svm",
                "num_cpus": 1,
                "gpu_type": "none",
                "batch_size": 16.0,
                "num_replicas": 1,
                "cloud": "aws"
            }
        },
        "estimated_perf": {
            "latency": 0.33690971999999997,
            "throughput": 502.8361084681255,
            "cost": 15.7
        },
        "response_time": 0.9708581701490014,
        "cv": 4.0,
        "utilization": 0.7
    },
    {
        "slo": 1.0,
        "cost": 18.4,
        "lam": 670,
        "node_configs": {
            "inception": {
                "name": "inception",
                "num_cpus": 1,
                "gpu_type": "v100",
                "batch_size": 48.0,
                "num_replicas": 3,
                "cloud": "aws"
            },
            "tf-resnet-feats": {
                "name": "tf-resnet-feats",
                "num_cpus": 1,
                "gpu_type": "v100",
                "batch_size": 48.0,
                "num_replicas": 4,
                "cloud": "aws"
            },
            "tf-log-reg": {
                "name": "tf-log-reg",
                "num_cpus": 1,
                "gpu_type": "none",
                "batch_size": 2.0,
                "num_replicas": 1,
                "cloud": "aws"
            },
            "tf-kernel-svm": {
                "name": "tf-kernel-svm",
                "num_cpus": 1,
                "gpu_type": "none",
                "batch_size": 24.0,
                "num_replicas": 1,
                "cloud": "aws"
            }
        },
        "estimated_perf": {
            "latency": 0.25733776,
            "throughput": 668.7297811607991,
            "cost": 18.294500000000003
        },
        "response_time": 0.9892702408135852,
        "cv": 4.0,
        "utilization": 0.7
    },
    {
        "slo": 1.0,
        "cost": 21.0,
        "lam": 683,
        "node_configs": {
            "inception": {
                "name": "inception",
                "num_cpus": 1,
                "gpu_type": "v100",
                "batch_size": 64.0,
                "num_replicas": 3,
                "cloud": "aws"
            },
            "tf-resnet-feats": {
                "name": "tf-resnet-feats",
                "num_cpus": 1,
                "gpu_type": "v100",
                "batch_size": 48.0,
                "num_replicas": 5,
                "cloud": "aws"
            },
            "tf-log-reg": {
                "name": "tf-log-reg",
                "num_cpus": 1,
                "gpu_type": "none",
                "batch_size": 2.0,
                "num_replicas": 1,
                "cloud": "aws"
            },
            "tf-kernel-svm": {
                "name": "tf-kernel-svm",
                "num_cpus": 1,
                "gpu_type": "none",
                "batch_size": 24.0,
                "num_replicas": 1,
                "cloud": "aws"
            }
        },
        "estimated_perf": {
            "latency": 0.25733776,
            "throughput": 688.3799999999999,
            "cost": 20.889
        },
        "response_time": 0.8905975152868748,
        "cv": 4.0,
        "utilization": 0.7
    }
]